branding/.git
branding/.gitignore
branding/README.md
branding/STYLE_GUIDE.md
branding/logos/AUTHOR
branding/logos/LICENSE
branding/logos/README.md
branding/logos/mdanalysis-logo.pdf
branding/logos/mdanalysis-logo.svg
branding/logos/mdanalysis-logo_square.pdf
branding/logos/mdanalysis-logo_square.svg
branding/logos/mdanalysis-ugm.png
branding/logos/mdanalysis-ugm.svg
branding/logos/banners/mdanalysis-banner-1280x144.pdf
branding/logos/banners/mdanalysis-banner-1280x144@300ppi.png
branding/logos/banners/mdanalysis-banner-1280x144@72ppi.png
branding/logos/banners/mdanalysis-banner-UGM-1280x144.pdf
branding/logos/banners/mdanalysis-banner-UGM-1280x144.png
branding/logos/banners/mdanalysis-banner-UGM-white-1280x144.pdf
branding/logos/banners/mdanalysis-banner-UGM-white-1280x144.png
branding/logos/icons/README.md
branding/logos/icons/apple-touch-icon-144-precomposed.png
branding/logos/icons/mdanalysis-logo.ico
branding/logos/rastered/mdanalysis-logo_bgwhite@150ppi.png
branding/logos/rastered/mdanalysis-logo_bgwhite@300ppi.png
branding/logos/rastered/mdanalysis-logo_bgwhite@600ppi.png
branding/logos/rastered/mdanalysis-logo_bgwhite@72ppi.png
branding/logos/rastered/mdanalysis-logo_square_bgwhite@150ppi.png
branding/logos/rastered/mdanalysis-logo_square_bgwhite@300ppi.png
branding/logos/rastered/mdanalysis-logo_square_bgwhite@600ppi.png
branding/logos/rastered/mdanalysis-logo_square_bgwhite@72ppi.png
branding/logos/rastered/mdanalysis-logo_square_transparent@150ppi.png
branding/logos/rastered/mdanalysis-logo_square_transparent@300ppi.png
branding/logos/rastered/mdanalysis-logo_square_transparent@600ppi.png
branding/logos/rastered/mdanalysis-logo_square_transparent@72ppi.png
branding/logos/rastered/mdanalysis-logo_transparent@150ppi.png
branding/logos/rastered/mdanalysis-logo_transparent@300ppi.png
branding/logos/rastered/mdanalysis-logo_transparent@600ppi.png
branding/logos/rastered/mdanalysis-logo_transparent@72ppi.png
docs/conf.py
docs/numpydoc_example.py
mdanalysis_sphinx_theme-1.3.1.dist-info/AUTHORS.md
mdanalysis_sphinx_theme-1.3.1.dist-info/LICENSE
mdanalysis_sphinx_theme-1.3.1.dist-info/METADATA
mdanalysis_sphinx_theme-1.3.1.dist-info/WHEEL
mdanalysis_sphinx_theme-1.3.1.dist-info/entry_points.txt
mdanalysis_sphinx_theme-1.3.1.dist-info/top_level.txt
mdanalysis_sphinx_theme-1.3.1.dist-info/RECORD
