Metadata-Version: 2.1
Name: mdanalysis-sphinx-theme
Version: 1.3.1
Summary: Modification to sphinx_rtd_theme
Home-page: https://github.com/mdanalysis/mdanalysis-sphinx-theme/
Author: MDAnalysis
Author-email: mdanalysis@numfocus.org
License: MIT
Classifier: Development Status :: 5 - Production/Stable
Classifier: License :: OSI Approved :: MIT License
Classifier: Environment :: Console
Classifier: Environment :: Web Environment
Classifier: Intended Audience :: Developers
Classifier: Programming Language :: Python :: 3
Classifier: Operating System :: OS Independent
Classifier: Topic :: Documentation
Classifier: Topic :: Software Development :: Documentation
Requires-Python: >=3.9
License-File: LICENSE
License-File: AUTHORS.md
Requires-Dist: sphinx_rtd_theme>=1.3
Requires-Dist: sphinx>=6.2.1
Requires-Dist: beautifulsoup4
Requires-Dist: python-slugify[unidecode]
Requires-Dist: css_html_js_minify
Requires-Dist: lxml
Requires-Dist: libsass
